jupyterlab_robodyno_blockly/__init__.py
jupyterlab_robodyno_blockly/_version.py
jupyterlab_robodyno_blockly/labextension/build_log.json
jupyterlab_robodyno_blockly/labextension/package.json
jupyterlab_robodyno_blockly/labextension/static/lib_index_js.6b0e7f3e193cc04d720c.js
jupyterlab_robodyno_blockly/labextension/static/lib_index_js.6b0e7f3e193cc04d720c.js.map
jupyterlab_robodyno_blockly/labextension/static/lib_index_js.6c8805b7a22b4c90ebf7.js
jupyterlab_robodyno_blockly/labextension/static/lib_index_js.6c8805b7a22b4c90ebf7.js.map
jupyterlab_robodyno_blockly/labextension/static/lib_index_js.9093f7763d6733901aa0.js
jupyterlab_robodyno_blockly/labextension/static/lib_index_js.9093f7763d6733901aa0.js.map
jupyterlab_robodyno_blockly/labextension/static/lib_index_js.b28c7fe4ca13c3e02ce5.js
jupyterlab_robodyno_blockly/labextension/static/lib_index_js.b28c7fe4ca13c3e02ce5.js.map
jupyterlab_robodyno_blockly/labextension/static/remoteEntry.68b6d73f731de2a10765.js
jupyterlab_robodyno_blockly/labextension/static/remoteEntry.68b6d73f731de2a10765.js.map
jupyterlab_robodyno_blockly/labextension/static/remoteEntry.8583027f93c9ab51effe.js
jupyterlab_robodyno_blockly/labextension/static/remoteEntry.8583027f93c9ab51effe.js.map
jupyterlab_robodyno_blockly/labextension/static/remoteEntry.c0f7c4619c69f05815cd.js.map
jupyterlab_robodyno_blockly/labextension/static/remoteEntry.e562fa1b84fbb361e05b.js
jupyterlab_robodyno_blockly/labextension/static/remoteEntry.e562fa1b84fbb361e05b.js.map
jupyterlab_robodyno_blockly/labextension/static/style.js
jupyterlab_robodyno_blockly/labextension/static/style_index_js.83ff921823f13d54402f.js
jupyterlab_robodyno_blockly/labextension/static/style_index_js.83ff921823f13d54402f.js.map
jupyterlab_robodyno_blockly/labextension/static/vendors-node_modules_blockly_core-browser_js.57fc0f1f329db79363c6.js
jupyterlab_robodyno_blockly/labextension/static/vendors-node_modules_blockly_core-browser_js.57fc0f1f329db79363c6.js.map
jupyterlab_robodyno_blockly-0.1.2.dist-info/LICENSE
jupyterlab_robodyno_blockly-0.1.2.dist-info/METADATA
jupyterlab_robodyno_blockly-0.1.2.dist-info/WHEEL
jupyterlab_robodyno_blockly-0.1.2.dist-info/top_level.txt
jupyterlab_robodyno_blockly-0.1.2.dist-info/RECORD
