Metadata-Version: 2.1
Name: jupyterlab-robodyno-blockly
Version: 0.1.2
Summary: The Robodyno Robot Motor for jupyter lab blockly
Home-page: https://pypi.org/project/jupyterlab-robodyno-blockly/
Author: ryan.zhang
Author-email: ryan@163.com
License: BSD 3-Clause License        
Keywords: Jupyter,JupyterLab,JupyterLab3,Robodyno,Blockly
Platform: Linux
Platform: Mac OS X
Platform: Windows
Classifier: Framework :: Jupyter
Classifier: Framework :: Jupyter :: JupyterLab
Classifier: Framework :: Jupyter :: JupyterLab :: 3
Classifier: Framework :: Jupyter :: JupyterLab :: Extensions
Classifier: Framework :: Jupyter :: JupyterLab :: Extensions :: Prebuilt
Classifier: License :: OSI Approved :: BSD License
Classifier: Programming Language :: Python
Classifier: Programming Language :: Python :: 3
Classifier: Programming Language :: Python :: 3.7
Classifier: Programming Language :: Python :: 3.8
Classifier: Programming Language :: Python :: 3.9
Classifier: Programming Language :: Python :: 3.10
Requires-Python: >=3.7
License-File: LICENSE
Provides-Extra: env
Requires-Dist: pyrobodyno ; extra == 'env'
Provides-Extra: test
Requires-Dist: coverage ; extra == 'test'
Requires-Dist: pytest ; extra == 'test'
Requires-Dist: pytest-asyncio ; extra == 'test'
Requires-Dist: pytest-cov ; extra == 'test'
Requires-Dist: pytest-tornasync ; extra == 'test'
